logstash/__init__.py
logstash/formatter.py
logstash/handler_amqp.py
logstash/handler_file.py
logstash/handler_tcp.py
logstash/handler_udp.py
logstash/mixins.py
python_logstash_g-0.7.0.dist-info/LICENSE
python_logstash_g-0.7.0.dist-info/METADATA
python_logstash_g-0.7.0.dist-info/WHEEL
python_logstash_g-0.7.0.dist-info/top_level.txt
python_logstash_g-0.7.0.dist-info/RECORD
