Metadata-Version: 2.1
Name: python-logstash-g
Version: 0.7.0
Summary: Python logging handler for Logstash.
Home-page: https://github.com/vklochan/python-logstash
Author: Volodymyr Klochan
Author-email: vklochan@gmail.com
License: MIT
Platform: UNKNOWN
Classifier: Development Status :: 4 - Beta
Classifier: Intended Audience :: Developers
Classifier: License :: OSI Approved :: MIT License
Classifier: Operating System :: OS Independent
Classifier: Programming Language :: Python
Classifier: Programming Language :: Python :: 2
Classifier: Programming Language :: Python :: 3
Classifier: Topic :: Internet :: WWW/HTTP
Classifier: Topic :: Software Development :: Libraries :: Python Modules
Classifier: Topic :: System :: Logging
